ColorReliefEditor/ColorReliefEdit.py
ColorReliefEditor/color_config.py
ColorReliefEditor/color_page.py
ColorReliefEditor/contour_page.py
ColorReliefEditor/elevation_page.py
ColorReliefEditor/file_drop_widget.py
ColorReliefEditor/hillshade_page.py
ColorReliefEditor/instructions.py
ColorReliefEditor/make_handler.py
ColorReliefEditor/make_process.py
ColorReliefEditor/misc_page.py
ColorReliefEditor/preview_widget.py
ColorReliefEditor/project_config.py
ColorReliefEditor/project_page.py
ColorReliefEditor/recent_files.py
ColorReliefEditor/relief_page.py
ColorReliefEditor/settings_page.py
ColorReliefEditor/tab_page.py
ColorReliefEditor/resources/Color.html
ColorReliefEditor/resources/Contour.html
ColorReliefEditor/resources/Create.html
ColorReliefEditor/resources/Elevation Files.html
ColorReliefEditor/resources/Hillshade.html
ColorReliefEditor/resources/Makefile
ColorReliefEditor/resources/Misc.html
ColorReliefEditor/resources/Project.html
ColorReliefEditor/resources/Settings.html
ColorReliefEditor/resources/default_color_ramp.txt
ColorReliefEditor/resources/default_relief.cfg
ColorReliefEditor/resources/relief_editor.cfg
ColorReliefEditor-0.4.0.data/scripts/color_relief.sh
ColorReliefEditor-0.4.0.dist-info/METADATA
ColorReliefEditor-0.4.0.dist-info/WHEEL
ColorReliefEditor-0.4.0.dist-info/entry_points.txt
ColorReliefEditor-0.4.0.dist-info/top_level.txt
ColorReliefEditor-0.4.0.dist-info/RECORD
