Metadata-Version: 2.1
Name: ColorReliefEditor
Version: 0.4.0
Summary: Creates hillshade images and color relief images from Digital Elevation Files using GDAL
Author: corb
Project-URL: Repository, https://github.com/corb555/ColorReliefEditor
Keywords: GDAL,GIS,editor,DEM,Elevation
Classifier: Intended Audience :: End Users/Desktop
Classifier: Topic :: Scientific/Engineering :: GIS
Classifier: License :: OSI Approved :: MIT License
Classifier: Programming Language :: Python
Classifier: Programming Language :: Python :: 3.8
Requires-Python: >=3.9
Requires-Dist: PyQt6>=6.6.1
Requires-Dist: appdirs~=1.4.4
Requires-Dist: YMLEditor>=0.1.19
